toggl_tally/__init__.py
toggl_tally/api.py
toggl_tally/cli.py
toggl_tally/filter.py
toggl_tally/report.py
toggl_tally/tally.py
toggl_tally/time_utils.py
toggl_tally-0.1.2.dist-info/LICENSE
toggl_tally-0.1.2.dist-info/METADATA
toggl_tally-0.1.2.dist-info/WHEEL
toggl_tally-0.1.2.dist-info/entry_points.txt
toggl_tally-0.1.2.dist-info/top_level.txt
toggl_tally-0.1.2.dist-info/RECORD
