Metadata-Version: 2.1
Name: toggl-tally
Version: 0.1.2
Summary: A rich CLI to track hours worked towards monthly targets with toggl
Author-email: Tim Wolff-Piggott <twolffpiggott@gmail.com>
License: GNU GENERAL PUBLIC LICENSE
Project-URL: Homepage, https://github.com/twolffpiggott/toggl-tally
Keywords: toggl,cli,track,toggl-api,command line
Classifier: License :: OSI Approved :: GNU General Public License v3 (GPLv3)
Classifier: Operating System :: Microsoft :: Windows
Classifier: Operating System :: MacOS
Classifier: Operating System :: POSIX :: Linux
Classifier: Programming Language :: Python :: 3.7
Classifier: Programming Language :: Python :: 3.8
Classifier: Programming Language :: Python :: 3.9
Classifier: Programming Language :: Python :: 3.10
Classifier: Programming Language :: Python :: 3.11
Requires-Python: >=3.7
License-File: LICENSE
Requires-Dist: click (>=8.1.3)
Requires-Dist: holidays (>=0.19)
Requires-Dist: pyyaml (>=6.0)
Requires-Dist: requests (>=2.28.2)
Requires-Dist: rich (>=13.3.2)
Provides-Extra: dev
Requires-Dist: pytest (>=7.2.1) ; extra == 'dev'
Requires-Dist: black (>=23.1.0) ; extra == 'dev'
Requires-Dist: flake8 (>=6.0.0) ; extra == 'dev'
Requires-Dist: ipdb ; extra == 'dev'
Requires-Dist: isort (>=5.12.0) ; extra == 'dev'
Requires-Dist: pre-commit ; extra == 'dev'
Provides-Extra: test
Requires-Dist: pytest (>=7.2.1) ; extra == 'test'
